{
    "38fc2bdc-5c5c-4c90-8d81-b4a78f85c41d": "\"며칠 전, 한 무리의 촉수들이 하수구에서 기어 나와 부랑자 두 명을 끌고 갔어요. 그 부랑자들은 갈기갈기 찢기는 것처럼 비명을 질렀습니다.. 저희는 거의 웃을 뻔했어요.\"",
    "f7de6b52-857f-46eb-95dc-9b98c0240ea4": "\"육체시장에 새로운 아시마르가 도착했습니다! 두 마리 사러 가야겠어요. 필레가 너무 달콤해요.\"",
    "44de9cb1-3728-48d3-b29e-5ed1b264ed5d": "\"알루시니라가 아루샬래를 기립니다! 그리고 그녀의 친구들도!\"",
    "dcba73b2-2857-4c61-b87c-008667b5f4a4": "\"나쁜 시대가 왔습니다. 바포메트의 창녀 헵자미라가 모든 것을 소유한 것처럼 행세하고, 모두가 그녀 앞에 머리를 조아립니다. 도대체 그녀는 누구이며 어디서 그렇게 많은 힘을 얻었을까요?\"",
    "ae8a4e1d-182e-445d-9092-d7079b81ff33": "\"바포메트의 데몬들이 우리 집에 마치 주인인 것처럼 들어와요! 저 개자식들! 하지만 데카라이트는 더 심해! 건방진 놈들! 다 쫓아내면 정말 좋을 텐데!\"",
    "98714ddf-0b99-4294-a54a-79a1174ec51b": "\"이것 봐요, 벨렉시아가 새로 좋아하는 거예요! 소문에 의하면 둘이 서로에게 푹 빠졌다고 해요 - 정말이에요! 사람들은 벨렉시아가 {mf|그|그녀}에게 하트를 주기 위해 매일 새로운 노예를 해부한다고 해요!\"",
    "47e3813b-8a5d-4fa0-a8f0-07f14e598611": "\"치바로는 낯선 사람에게 이를 물려고 했어요. 물린 깊이가 충분하지 않았던 모양입니다.. 그 결과는 치바로에게 불행했습니다.\"",
    "8d56f28f-a60b-470c-b8e2-c46934667a08": "\"저주, 저건 {mf|him|her}이야! 천사를 알루시니라로 데려온 자! {mf|그|그녀}에게 자리를 비켜주는 게 좋을 거야.\"",
    "a96c395e-0f91-4400-85c4-16a25ab0d7e9": "\"정말 배틀블리스의 챔피언을 물리쳤어?! 대단하네요! 진짜 학살이었다고 들었어요!\"",
    "2f52e773-f8ba-47e9-8a5f-f4a256eb274e": "\"단돈 천 금화만 주면, 당신의 적을 가장 못된 콰짓처럼 처단해 주겠소. 암살자 길드의 일원으로서 그 결과에 목숨을 걸겠습니다.\"",
    "62002f70-5aa7-41e8-ad1b-9ce2117a71a3": "\"하, {mf|그|그녀}를 잘 알아요! 이 놈이 바로 육체시장에서 학살을 일으킨 놈이야! 이제 모든 노예상들이 경호원을 대량으로 사들이고 있어!\"",
    "cffd185c-ebf0-4aee-8328-1578bb43f6c4": "\"안녕, 아자타 킬러! 저 외지인 디말치오가 못을 박기 전에 고통스럽게 만들었으면 좋겠어!\"",
    "815d163b-7c3a-429c-a4e3-a798defee20d": "\"이봐요! 사바멜렉의 저택을 부순 게 바로 당신이죠? 분명 너한테 화났을 거야!\"",
    "f533f6f0-1046-41cf-8fa2-9b6f278ccec7": "\"야, 저거 메피트 슬레이어다!!\"",
    "7e2823f4-adea-4a3d-af66-697847a91f43": "\"{mf|그|그녀}의 벨렉시아를 쓰러뜨렸다니 믿을 수가 없어요! 그녀는 너무 강력해서 불사신처럼 보였어요!\"",
    "5412096d-51fd-42ce-a5a9-c358016c975b": "\"블롭이라는 친구가 있었어요. 그는 검투사였어요. 한번은 블롭이 손가락이 부러지는 가벼운 부상을 입어 경기장 치유사에게 갔어요. 그런데 다음 날 치유사가 돌아와서 블롭이 수술 도중 사망했다고 말했어요!\"",
    "63cba2b4-5385-4ffc-bb2b-96c9c6ee83fe": "\"그 쓰레기 같은 놈, 이르만갈레스가 싫어. 겔더팡과의 대결을 약속했는데.. 그러자 리그 전체가 저를 덮쳐서 쓰러뜨렸어요. 챔피언은 경기장에 나타나지도 않았어요.\"",
    "ae2de592-bcf8-4587-9fd0-7b4c751810fa": "\"저는 녹티큘라를 좋아합니다. 그녀는 중하층부의 모든 쓰레기를 단호한 손길로 통제하면서도 심각한 데몬들을 방해하지 않죠. 진정한 통치자는 그렇게 행동해야 합니다.\"",
    "6cf944ca-a436-445e-b22d-b5f39db2c661": "\"녹티큘라가 그저 보잘것없는 존재였던 시절이 기억납니다. 비리아박수스가 이곳의 모든 것을 책임지고 있었죠. 이제 그녀는 자신이 심연의 왕국의 여주인이라 주장합니다! 비리아박수스는 어디 있지? 시체처럼 죽었죠.\"",
    "dd3bcda5-f392-4894-88f6-eb8b52b1159a": "\"한때는 성공한 노예였어요.. 하지만 샤미라의 말 한 마디에 이 쥐구멍으로 추방되어 여기까지 오게 되었습니다.\"",
    "ddb5f89c-564b-4575-929e-c6853def3f91": "\"저도 암살자를 위해 일하고 싶어요. 목을 자르고, 내장을 흘리고, 돈을 받는 거요? 그게 바로 인생이죠!\"",
    "87b064ea-15c9-4194-9984-387e47551329": "\"저 간수들의 목을 부러뜨릴 거야! 온갖 쓰레기들이 끊임없이 이 숙소를 돌아다녀요! 최근에도 도둑 열댓 명이 내 저택에 침입했습니다.. 그 후, 벽에 붙은 끔찍한 내장을 모두 긁어내야 했어요. 글쎄요, 저는 개인적으로는 아니지만 노예들은 그래야만 했어요!\"",
    "817a91df-3483-42ef-b092-d771ab4d15d3": "\"지루해.. 육체시장에 가서 노예를 사서 굿을 해야겠어. 그러면 오락거리라도 되겠지.\"",
    "eb6aa1ea-050f-4931-bf30-05e8370222d2": "\"방금 육체시장에서 노예를 배송받았습니다. 절반은 결함이 있어요! 비뚤어지고, 절뚝거리고, 반쯤 죽었어! 시장에 팔기 전에 환상을 심어놨어! 그 개자식을 다시 보면 맨손으로 간을 뜯어버릴 거야!\"",
    "db265531-6a12-4547-a2ea-f3ad6a7d8a2c": "\"벨렉시아 부인이 내 재능을 알아봐 주었더라면! 얼마나 호화로운 삶을 살 수 있었을까!\"",
    "36869a0f-711b-4b96-8dbb-71f85ebd0de1": "\"새 노예 {mf|sir|ma'am}을 위한 훌륭한 감독자가 필요하다면 더 이상 찾아보지 마세요. 내가 그들에게 순종하도록 가르치겠다.\"",
    "a954d88f-0a69-4530-9b9a-a80f8dfc0d71": "\"{mf|그|그녀}의 골라리온의 모든 노예를 사들이는 사람 아닙니까? 노예들은 {mf|그|그녀}만 얘기하고, {mf|그|그녀}를 {mf|god|goddess}처럼 취급하죠.\"",
    "e080fe92-7d8f-41cf-af2a-3960a522d6a3": "\"다 헛소리겠지만, 사람들은 진짜 천사는 {mf|그|그녀}를 {mf|그|그녀}의 보디가드로 데리고 다닌다고 하죠! 심연에서!\"",
    "627109f8-d0b2-40b7-8282-f5467e889eec": "\"파열의 휴거의 리셉션에 초대되어 정말 멋져요!\"",
    "1bd39759-b9b4-44a5-86ad-8fadb2d87513": "\"칼을 뽑아 경비병을 찔러야 할 때입니다.. 알루시니라는 자유의 도시다...\"",
    "cf674532-c948-4f32-9e56-23b426a75541": "\"레이디 벨렉시아는 알루시니라 귀족의 진정한 리더입니다!\"",
    "024f21f4-799e-4aa5-a326-cf746eb87faa": "\"배틀행복의 챔피언 만세! 겔더팽이 모두를 갈기갈기 찢어버릴 것이다! 겔더팽 만세!\"",
    "955b9291-ad2a-4dff-a5d4-25a3053dbdd0": "\"봐요, 녹티큘라의 애완동물이 저기 있네요! 어떻게 {mf|그|그녀}의 이렇게 칭찬을 많이 받을 수 있지?!\"",
    "7d8303c6-5664-4fc3-b7a4-334ca7b5a082": "\"봐요, 샤미라의 더러운 일을 하는 새로운 {mf|소년|소녀}입니다! 사람들은 그녀가 {mf|그|그녀}에게 비밀 임무를 맡긴다고 해요!\"",
    "1dd01458-97fe-40fb-b745-c51e950614aa": "\"배틀블리스의 경기가 최근 들어 몹시 지루해졌습니다. 누가 이길지 처음부터 알 수 있어요. 처형이 아닌 전투를 보고 싶어요!\"",
    "a9f900d9-6d8b-4867-b37e-259408cb7268": "\"녹티큘라는 폭군이자 악랄한 암캐입니다. 누군가 왕좌에서 긁어내서 목을 비틀어버렸으면 좋겠어요. 정말 싫어요.\"",
    "24df3e62-8364-4d1b-9fae-6a8ff2ccd974": "\"녹티큘라, 바포메트, 데스카리는 서로 사이가 좋은 척합니다. 하지만 그건 헛소리예요. 그들은 기회만 있으면 기꺼이 서로의 목을 치려고 할 겁니다. 그 과정을 지켜보는 재미가 쏠쏠하죠.\"",
    "daff4067-e376-441a-ae1e-bef9e7d40edc": "\"샤미라에게 정정당당하게 맞설 수 있는 기회는 절대 없어요! 그녀는 널 씹어서 다시 뱉어낼 거야. 눈도 깜빡하기 전에 빈민가로 돌아갈 거야. 샤미라가 너한테서 원하는 게 있으면 가서 찾아서 다른 사람에게 팔아서 돈을 많이 벌어!\"",
    "944ac01a-a297-4a01-a57c-92328519c680": "\"악몽을 잣는 자'를 찾던 낯선 사람이군요? 용감하군, {mf|그|그녀}에게 박수를 보내야겠어! 스피너는 위험한 물건이에요.\"",
    "2ea85f23-1679-4682-b9c6-784db2aba7c7": "\"오, 윌로두스, 그 한심한 자식. 불쌍하기 짝이 없군. 그의 머리에 대가를 치렀으니 이제 그는 포위당한 요새처럼 궁전에 앉아 있겠지. 그래도 그는 결국 파멸할 겁니다.\"",
    "5dd2b6bd-4654-47cc-9106-99892519c4f8": "\"암살자 길드 본부가 폐허가 되었다고 소문이 났어요! 그 안은 제대로 된 도살장이었어! 그리고 그 낯선 사람이 모든 책임을 져야 합니다!\"",
    "ed42ef8c-37b5-45f2-9757-9bb9ee665e00": "\"사람들은 헵자미라가 그녀를 대신해 일을 할 일꾼을 고용하고 있다고 말합니다. 일꾼이 엄청나게 많다고요, 군대 전체가. 그녀를 찾아야 할지도 모르겠어요...\"",
    "d473a84e-a258-4632-8402-ab63c2290f28": "\"사람들은 미나고가 이 낯선 사람에게 앙심을 품고 있었다고 말합니다! 둘이 충돌했는데 미나고는 지금 어디 있죠? 그녀는 더 강한 사람을 상대로 움직이지 말았어야 했어요.\"",
    "ab79b3f0-d382-48d2-985d-b346bdfb6a00": "\"사람들은 인구가 없는 많은 섬들이 이 심연의 차원으로 떨어졌다고 말합니다. 최근에 뭔가 잘못되고 있습니다.\"",
    "7b4e1d26-4093-44c2-81bb-8959ef9b213e": "\"암살자 길드의 새로운 멤버라는 소문이 돌고 있습니다. 알루시니라 전체에서 가장 용맹한 암살자라고 합니다! 명성이 대단하군요!\"",
    "1645cb39-442b-4726-81e6-f4a9d0422939": "\"샤미라는 너무 자만심에 가득 차 있어요. 녹티큘라에게 모든 걸 빚지고 있는 건방진 신인이에요! 물론 여전히 위험하긴 하지만요. 전 그녀의 적이 되고 싶지 않아요.\"",
    "7943b867-f271-4473-9197-d06c9422cf69": "\"가끔은 화풀이하러 로어 시티에 가기도 해요. 그 한심한 생명체들을 한두 마리 죽이고 나면 잠시나마 분노가 사라지죠.\"",
    "3500ee5d-591c-460d-bab6-7e3332d87891": "\"나헨드리안 리그의 저주받은 전사들에게 절단된 전직 투기장 검투사를 위해 동전을 아끼지 마세요.\"",
    "e700b4b8-9ec0-4a6f-8e48-2c1607838990": "\"육체시장은 문을 닫았습니다! 지금 거기서 망할 나무가 자라고 있어! 이제 제대로 된 노예를 살 수 없어! 모두 {mf|그|그녀} 때문이야!\"",
    "08fb0067-649b-4665-a6b3-368f0f1f74e2": "\"나헨드리안 리그가 경기장을 지배합니다! 난 그들을 좋아해! 나힌드리안 갑옷과 나힌드리안 도끼를 사야겠어요!\"",
    "5f766b3b-187c-47aa-9e3a-cf15a777a994": "\"당신이 여기 있다는 사실은 당신이 알루시니라 상류사회에 받아들여졌다는 것을 의미합니다\"",
    "fcea3a9b-5e17-496d-a6da-0ba98e456763": "\"얼마 전 한 갱단이 배드 럭이라는 선술집을 난장판으로 만들고 주인을 죽였어요. 이제 이 선술집은 다른 사람의 소유가 되었습니다.\"",
    "94c97928-e152-4930-98e6-8013f0945e7e": "\"다른 차원에서 온 낯선 남자가 싸게 살 물건을 찾으며 이곳을 돌아다니고 있었어요. 그래서 우리가 그에게 멋진 상품을 권했더니 경비원들이 바로 게이트에서 그를 붙잡아갔어요! 정말 웃겼죠!\"",
    "a8f743d6-f189-4640-af6b-a771542a6b50": "\"벨렉시아는 지루해졌습니다. 그녀는 다시 한 번 젊은 인재를 찾고 있습니다! 그녀에게 깊은 인상을 남기는 사람은 호화로운 삶을 살게 됩니다. 그렇지 못한 사람은 다시는 볼 수 없습니다.\"",
    "310a5891-da50-4976-b615-3e3910cb4102": "\"조심하세요, 새로운 주인님 그림자 데몬이 등장합니다!\"",
    "a1824f87-e170-4256-a356-7c6334dd43e2": "\"{mf|그|그녀}의 {mf|그|그녀}를 성문에서 막으려던 경비병들을 학살했다고 들었습니다! 끔찍하군요!\"",
    "d10a5032-3f61-4955-9eac-418718712f90": "\"우와, 윌로두스의 살인범이 살아있네! {mf|그|그녀}의 자신의 궁전 정문 바로 앞에서 불쌍한 녀석을 죽였어! 그리고 데몬은 울부짖으며 자비를 구걸했어!\"",
    "b2229783-d419-41b4-a522-b810b5d80fb8": "\"녹티큘라는 왜 낯선 사람들을 도시에 들여보냈을까요? 그들은 계속 돌아다니면서 어울리지도 않는 곳에 코를 들이밀고 있어요! 우리가 힘을 합쳐서 저들의 오물을 치워야 해요!\"",
    "0edabf5a-e24a-45c9-82dd-e08aa030c706": "\"소문에 따르면 치바로가 미나고로부터 서큐비를 장악했다고 합니다. 하지만 둘 다 살아있으니 모종의 거래를 했다는 뜻이죠.\"",
    "1054937e-6dec-4dee-b9bc-c1a83a29cf79": "\"와, 저 낯선 사람 보여요? 사작시스 경이 장식품을 줬어요!\"",
    "3aa41fcb-cbce-40d9-9a32-e19b332f9df4": "\"그 미친 년, 벨렉시아는 절대 상대하지 마세요. 지루해지면 끔찍한 짓을 하기 시작하거든!\"",
    "69d81203-0545-4820-ac73-529df6f75942": "\"그 짐승 같은 보에티엘을 죽였잖아! 다음엔 헵자미라를 노린다는 게 사실이야?\"",
    "5e24d508-764c-4510-8209-0d9970467829": "알루시니라 육체시장의 금화입니다. 동전에 새겨진 문양은.. 또 다른 동전을 묘사합니다.",
    "df297a79-e6b1-4a0a-8048-4af57762d86a": "알루시니라에 있는 불운의 선술집에서 나온 금화입니다. 동전에는 어떤 데몬의 송곳니가 쓰러져 있는 디자인이 새겨져 있습니다.",
    "b598658a-7a29-431d-8d23-853987882a1e": "한때 샤미라의 소유였던 금화입니다. 동전에는 타오르는 왕관이 새겨져 있습니다.",
    "a0afe6de-9ef2-4c33-9bdf-b86fc0c670bf": "헤랙스의 소유였던 금화입니다. 음란한 그림이 새겨져 있습니다.",
    "73d07649-523b-463e-872f-930051d62c7f": "제클렉스의 소유였던 금화입니다. 두 개의 교차된 칼날을 묘사한 디자인이 한 면에 새겨져 있습니다.",
    "c6fd7163-2146-4e9a-bef9-5522f6fc9f3c": "발러 다라잔의 소유였던 금화입니다. 데몬 로드 바포메트의 표식이 동전의 얼굴에 새겨져 있습니다.",
    "8968c30f-6ca5-4eef-af8f-79a6ce14d7b7": "서큐버스 벨렉시아의 소유였던 금화입니다. 동전에는 박쥐의 날개가 새겨져 있습니다.",
    "93ed9825-a206-4136-bf9c-9a6db543b513": "사람의 손가락에 맞는 크기가 아닌 거대하고 조잡하게 만들어진 반지.",
    "47c2516d-8dd5-419e-bef0-940fb2618626": "타나토틱 타이탄의 언어로 새겨진 신비한 룬으로, 강력하고 불안한 기운을 뿜어냅니다. 룬에 잠자고 있던 마법이 깨어나서이 고대 물체가 일종의 마법에 걸린 장치라는 것은 의심의 여지가 없습니다.",
    "6faef75e-402f-491c-a287-429a2f81ae24": "타나 토틱 타이탄의 언어로 새겨진 신비한 룬.",
    "5d016c09-ef3e-46f1-a334-87ef49c67462": "타나토틱 타이탄의 언어로 새겨진 신비한 룬입니다. 룬이 견뎌온 조작으로 인해 당황스러운 오라가 룬에서 발산됩니다.",
    "f1b4e5c2-edb0-4e0f-983e-80a79b9f56e5": "타나토틱 타이탄의 언어로 새겨진 신비한 룬입니다. 룬에서 발산되는 불편한 기운이 더욱 뚜렷합니다.",
    "74e2dfd7-6425-4a6e-bf39-a64e8153d1a4": "가공되지 않은 보라색 수정로 내구성이 뛰어납니다.",
    "68afd141-da76-4b3a-be4d-ac82426999da": "데몬의 피로 마법에 걸린 반지.",
    "7d14fc38-8897-4441-ad39-48b19e98eaf5": "검은 뼈로 조각한 정교한 열쇠입니다. 알루시니라의 전 통치자 지포리안에 따르면, 이 열쇠로 도시의 많은 문을 열 수 있다고 합니다.",
    "fedf8f7b-58b2-42a6-ab11-f0fa36e97b4e": "검은 뼈로 조각한 정교한 열쇠입니다. 한때 지포리안의 소유였던 이 열쇠는 매우 귀중한 물건일 가능성이 높습니다. 그렇지 않았다면 방랑자는 오래전에 이 우아한 조각을 동전 몇 개와 교환했을 것입니다. 하지만 이 열쇠를 사용하려면 먼저 올바른 문을 찾아야 합니다.",
    "31b1e398-c360-42db-9e1f-3617da52cd95": "불운 선술집의 금화",
    "b5a93d7f-cb64-4cb8-8339-b1ba43d3804e": "전투의 행복에서 얻은 금화",
    "5b99d932-7a63-400a-8df6-d05fbb9fe590": "육체시장의 금화",
    "22f15efd-b755-4dee-9edd-4122bb6871c7": "바포메트의 표식이 있는 금화",
    "d468be01-f875-4d7b-89d5-d75a075a8bc6": "헤랙스의 황금 동전",
    "ddf67ced-407a-497e-a0a4-dd60a66ba1ad": "나헨드리안 수정",
    "2a47f001-6f2c-4d23-a29b-d26589a8ae2b": "시니어 가드",
    "2315f62e-fee0-4d5a-87d8-8b0838fc2e92": "샤미라의 금화",
    "6f4fb6cf-5524-4ab9-90e2-d5144d4ae732": "이야기꾼의 나침반",
    "545ea158-6222-49ca-81de-f5fdea92b799": "타나토틱 타이탄의 인챈티드 룬",
    "4154ba08-daa3-4371-97e5-216c249c2e74": "타나토틱 타이탄의 위대한 룬",
    "a7838db9-ba80-4ca6-a4e9-561bd4256b00": "타나토틱 타이탄의 마이너 룬",
    "55d12cff-4139-49df-ac5d-fbf1d464c13e": "타나토틱 타이탄의 진정한 룬",
    "5ababbb9-841e-48cf-80b9-e388854a0f62": "알리니아 섬의 깊은 곳에서 나힌드리아 수정을 찾는데 도움이 되는 이야기꾼의 나침반입니다.",
    "8f523faf-4d2e-4d0a-aacd-74d08fc2cd40": "벨렉시아의 금화",
    "d1e2b9da-caea-4d1d-89e8-4f7630b05098": "제릭스의 마법에 걸린 반지",
    "ffd95655-1a13-41e2-8a6c-ccb232dfe8f5": "제릭스의 반지",
    "d1030394-1970-49c3-ba16-db6afb7f4395": "지포리안의 열쇠"
}