{
    "56b76988-f220-4eea-b831-d816849d26eb": "\"죽느니 식인종이 되는 게 낫다고 했잖아! 바보들은 무의미한 쥐떼처럼 마지막 부스러기를 놓고 싸웠습니다! 그런 동료들은 짐일 뿐이야. 시스후드의 은신처를 뼈로 장식하기 위해 생존자들을 죽였어. 나만 제정신으로 남았기 때문에 나머지 장비와 보급품은 내가 가져갔어.\n모든 걸 가져갈 수는 없어요. 코스트치치의 하인들에게서 안전하게 지키기 위해 일부를 숨겨야 해요.\"",
    "979bee19-2816-4c6e-a5b0-546eb34b42c7": "\"얼어붙은 군주가 패배했다는 사실이 아직도 믿기지 않습니다. 하지만 의심할 여지가 없습니다. 저와 시스후드의 다른 제자들은 모든 보호를 잃었습니다. 추위가 이렇게 날카롭고 무자비하게 느껴진 적은 없었습니다. 우리의 적인 코스트치치의 하인들은 추위를 훨씬 더 잘 견뎌내니 많은 사람들이 타락한 스승을 버리고 살인자의 편을 든 것은 당연합니다. 우리는 이전 동지들로부터 도망치고 있습니다.\n신참 중 한 명이 얼어 죽었습니다. 손가락이 마비될 때까지 그의 몸에 룬을 새겼지만 마법 눈보라를 피하기엔 역부족이었어요. 시체를 가져가야 할까요? 보급품이 떨어지고 있어요.\"",
    "5f17ac35-f878-4877-aee5-99ec2919186a": "\"제 감방 동료는 말이 많았어요. 그는 비밀 통로를 통해 고문실을 탈출할 수 있다고 말하며 그 통로를 여는 방법을 설명했습니다. 그 통로는 지역 주민들을 공포에 떨게 하는 키톤으로 연결되는 통로였어요. 저는 지쳐서 쓰러질 때까지 그 통로를 걸어 내려갔습니다. 깨어났을 때 저는 제 감방으로 돌아왔어요. \"주인\"에게로 가는 비밀 통로는 없었습니다. 그것은 죄수들을 괴롭히는 또 다른 방법이었을 뿐입니다.\"",
    "e744f7d3-e67c-41f6-b390-4a81e2a1977f": "\"오 얼어붙은 주님! 당신의 숭배는 더 이상 존재하지 않으며 당신을 찬양 할 사람이 남아 있지 않습니다. 육체가 약한 사람들은 멸망했고 영이 약한 사람들은 당신에게서 돌아섰습니다. 사기꾼이 당신의 영역을 점령했을 때, 당신이 가장 강력한 주문으로 우리를 축복하지 않았을 때, 당신의 목소리가 사라 졌을 때 - 그때마다 불충실 한 사람들은 당신의 이름을 저주하고 떠났고, 저 혼자 당신의 성전에 남아있었습니다. 저의 믿음은 결코 흔들리지 않았습니다. 주님은 당신의 가장 위대한 계획을 밝히시고 가장 신성한 보물 인 당신의 영혼의 귀중한 조각을 저에게 맡기 셨기 때문입니다.\n당신의 천재성 앞에 절을 올립니다. 그 누구도 그토록 비전적이고 독창적 인 계획을 고안하지 않았기 때문에 죽음조차도, 심지어 경멸과 망각조차도 위대함을 향한 당신의 길에서 단순한 단계가되었습니다. 영광의 시대가 올 것이지만 먼저 침묵의 시대를 통과해야합니다. 당신이 정당한 주인으로 돌아 오려면 세상은 당신의 이름을 잊어야합니다.\n당신의 영혼의 다른 파편들이 합당하지 않은 사람들의 몸을 차지한 것은 중요하지 않습니다. 나는 진실을 보았 기 때문입니다. 당신이 심연에서 잠자는 동안 당신의 파편들이 필멸의 세계를 방황하는 동안 당신은 빙하가 미묘하지만 불가피하게 전진하는 것처럼 두 세계를 서로 더 가깝게 만들고 있습니다.\n한때 당신의 거대한 종들이 고향이라고 불렀던 땅은 이제 사르코리스라는 이름을 지니고 있습니다. 그곳에는 한심한 신들에게 기도하는 무지한 바보들이 살고 있으며, 그 중 한 명은 당신의 영토를 빼앗은 바로 그 사기꾼입니다. 그들 중 누구도 심연이 다가오는 것을 보지 못합니다. 당신의 계획의 마지막 단계가 실현되는 것을 목격하기 전에 백 세대의 필사자가왔다 갔다 할 것입니다. 그러나 당신은이 얼음 산등성이 사이에서 영생의 선물을 저에게 주셨습니다. 그리고 예언이 이루어질 때, 심연이 찢어지고 당신의 얼음 바람이 사르코리스를 가로 질러 노래 할 때, 나는 당신의 숭배를 되살리기 위해 그곳에있을 것입니다. 당신을 환영하고 당신의 군대를 이끌고 필멸자의 세계를 정복하겠습니다.\n시스후드에게 영원한 영광을! 그분의 뜻이 이루어지고 그분의 왕국이 심연과 골리온에 임하기를!\"",
    "a5d47df3-32a6-432b-99c8-c313d56d8421": "\"잊혀진 악마에 대한 연구\"",
    "9829fec9-0357-4c3b-b135-ffe9045b6351": "\"고마워요.\"",
    "3da4435c-0049-4c36-b3a4-ceeca146dac1": "\"흰 깃털 부족의 잉군이 쓴 족장 흐라즈크의 말입니다.\n나는 거인족의 가장 위대하고 강력한 족장, 흐라즈크다. 젊은이들은 위대한 족장들의 선행과 현명한 생각을 알아야 하므로 나는 부하들에게 글을 쓸 수 있는 노예를 잡으라고 명령했다. 그는 우리 부족의 역사와 우리가 어떻게 최강의 부족이 되었는지 기록할 것입니다.\n한때 우리는 강하지 않았어요. 다른 부족들이 우리를 사냥하고, 좋은 곳에서 쫓아내고, 사냥꾼을 잡아 잡아먹었죠. 우리는 살아남기 위해 점점 더 산속으로 후퇴해야 했습니다. 그곳에는 큰 짐승도 인간도 없었습니다. 배고픈 삶이었죠.\n산에서 우리는 뼈를 발견했습니다. 아주 오래된 뼈였지만 얼어붙은 고기 조각이 조금 남아 있었어요. 난 족장이니까 가장 좋은 음식을 구할 수 있었죠. 가장 맛있는 것을 찾기 위해 뼈를 파헤치기 시작했을 때 뼈들이 말을 걸어왔어요! 아주 사나운 눈보라 같은 목소리로 말없이 말했어요. 그 목소리는 힘과 영광, 그리고 많은 음식을 약속했어요. 날카로운 얼음 조각이 제 뼈에서 나와 제 손에 떨어졌어요. 그 순간 모든 것이 바뀌었어요. 지금은 운이 좋았어요. 나는 항상 사슴을 잡을 곳과 사람을 잡을 곳을 알고 있습니다. 내 코는 항상 올바른 길을 가리 킵니다. 이제 우리는 결코 배고프지 않습니다.\n나는 강인하게 태어났어. 족장이 되기 위해 아버지를 죽였어요. 아버지는 나보다 키가 컸어! 그는 맨손으로 사슴을 두 동강 낼 수 있었지만 나는 목을 졸라 죽이고 내장을 먹었지. 전에도 강했지만 지금은 내가 제일 강해! 하즈크가 제일 강해! 최고라고! 우리는 산에서 돌아왔어. 이제 최고의 사냥터를 찾았어. 다른 부족들은 우릴 두려워해.\n하지만 난 아직도 그 목소리가 들려. 그리고 난 고대에 대한 꿈을 꿔. 이 뼈들이 서리 거인의 뼈라는 걸 알았어요. 그 거인들은 아주 크고 무서웠지만 오래 전에 모두 죽었어. 그들은 먼 산에 사는 뼈의 주님을 섬겼어요. 그들은 적들의 피로 그분의 표식을 그렸어요. 세 손가락이 달린 손. 그분은 그들에게 힘을 주셨고, 이제 그 힘은 내 것이 되었습니다. 그분은 더 많은 것을 주실 수 있습니다. 우린 그를 잘 섬기기만 하면 돼 뼈의 주님이 뭘 원하시는지 모르겠어. 나는 그분께 제물을 드리고 피로 그분의 표식을 그리지만 그것만으로는 충분하지 않습니다. 그분의 뜻을 배우고 실천하겠습니다. 그러면 우리는 서리 거인처럼 크고 강해질 것입니다. 우리는 원하는 사람은 누구든지 잡아먹을 것이고, 뼈 주님은 먼 산에서 내려와 세상을 얼리고 얼어붙은 폐기물을 다스릴 것입니다. 이런 것들은 말하기 무섭지만 난 꿈을 봤어. 반드시 그렇게 될 거라는 걸 알아요.\n이것이 우리의 영광스러운 이야기입니다. 이제 젊은이들도 읽을 수 있습니다.\n하즈크가 말을 많이 해서 목이 아파요. 뭐 좀 먹어야겠어. 노예가 글을 다 썼나?\n\"데스나 제발 살려주세요 안 돼요 안 돼요\"",
    "eb76b3ea-4d2f-48b2-b472-36629ab82b72": "\"이곳은 모든 색을 삼키는 어둠으로 가득 차 있습니다. 내가 낮빛을 그리워하는 동안 그림자계의 주민들은 그들만의 아름다움을 지니고 있습니다. 페츨링의 눈은 정말 놀라운 색채로 반짝입니다! 그럼에도 불구하고 나는 조심해서 이 어두운 성채 밖에서 야영을 하기로 결정했어. 시넷의 가문을 욕되게 하지 않겠어. 내일은 어둠의 중심부로 들어가 셸린의 은총을 가득 채우고 폭정으로 이 땅을 오염시키는 괴물을 없애겠습니다.\"",
    "2d37e815-066f-4f9b-a287-afa5c539ff1f": "\"이 끝없는 밤에 시간은 모든 의미를 잃었습니다. 나는 혼자였고 때로는 몇 년 동안 혼자 있었던 것처럼 느껴지기도 합니다. 이곳에 처음 왔을 때 저주했던 고문관이 얼마나 그리운지. 무수한 어둠과 외로움의 시간에 비하면 고문은 즐거움일 것입니다.\n곧 다 끝날 것이다. 그들은 내가 특별 손님이기 때문에 나를 주인에게 데려다 주겠다고 약속했다. 아마도 그는 나에게 죽음을 허락 할 것입니다-빠르든 느리 든 상관 없습니다. 이 글을 읽고있는 사람은 누구든지 당신에게 소중한 모든 것을 잃기 전에 도망 치십시오...\"",
    "103750ae-ca06-413a-99fa-bd29fc02056d": "\"태양이 없으니 낮과 밤이 어떻게 지나가는지 알 수 없습니다. 얼마나 오랫동안 이 지하 감옥을 헤매며 고통과 비참함만 보았습니까? 나는 수십 개의 감방을 열었지만 죄수들은 자유를 원하지 않고 자신에게 가해지는 고통과 괴로움을 환영한다. 고문관들은 저를 오랜 지인이라며 반갑게 맞이하고 방해하지 않습니다. 내 임무는 더 이상 비밀이 아니다. 셸린의 성기사가 여기 있다는 건 모든 그림자가 알고 있다.\n나는 새끼 한 마리가 울고 있는 감방에 침입했다. 셸린은 사랑이 치유한다고 가르쳤고, 나는 그를 위로하고 싶었다. 그는 여기서 위로를 갈망하는 유일한 사람이었습니다... 고문관이 어둠 속에서 갑자기 나타났어요. 그는 문을 쾅 닫으며 내가 두고 온 칼과 방패를 빼앗아 갔다. 이제 나도 죄수가 되었습니다.\"",
    "3c068786-c068-4323-b7d2-7244f966784c": "다양한 켈리드 장비로 가득 찬 가방.",
    "4f479ee3-fdce-4f5c-81de-d392a1bff9a5": "허브 향이 나는 흐린 액체. 요정이 불러일으키는 사랑의 마법을 깨뜨리는 힘이 있습니다.",
    "1b6e5541-6cf6-415c-afd6-d793d1518aa7": "죽은 고블린",
    "de01ef23-f4c0-4d3a-b4d1-e3596dd56002": "용의 몸에서 거대한 열쇠가 발견되었습니다.",
    "1ef91d56-3b41-40a1-989d-49a4cbac48b6": "페이의 사랑의 마법을 깨뜨리는 물약의 필수 재료입니다.",
    "75d72dd3-66f2-4d14-9687-c1ada209035d": "절대 어둠",
    "c59191e5-6cc0-430a-bfd0-743271c76ba7": "날렵한 소검 +2",
    "6e7c0366-be8c-47ed-8e65-ff9ba4af7847": "자연의 소환 부적",
    "da1513eb-91b6-484d-b833-b72dcd56abee": "매혹 방지 물약",
    "4d2be660-ccf8-4feb-8b0d-2a7b72114ad6": "아스자이트",
    "8914c287-2257-4aed-b786-a3419528d09f": "검은 거울 조각",
    "d3d36d73-de05-4445-a35b-c0906cb6f51c": "피의 눈물",
    "1bb757fe-ce83-496c-a2cd-420df5e0e2cd": "쥐의 부츠",
    "e9dd4912-87fb-470a-ad5c-09b3f8fbd00b": "정육점 칼",
    "bc2bf5e2-5312-436a-a3e8-cbf8a7000776": "동굴 야수 독",
    "5336223d-0bb1-4470-ba1d-950784e7c35f": "광신도의 태블릿",
    "92d4a475-5834-47e9-995b-8b03e062a957": "눈부신 단검",
    "c34149d0-345a-4518-a1ac-ccbeaec3e41b": "사슴 가죽 낙서",
    "783e8dc9-d993-4057-86a2-fc68a9ed09f9": "어둠의 디스펠러",
    "5b3545ae-514b-499c-9e3d-574a9346a193": "드래곤 키",
    "01efadc0-3186-4be0-af38-8fa3547ff56b": "드루카이트",
    "95f5d2e0-f174-4463-974b-e58462529a79": "드루카이트",
    "84adabb5-d0bf-4fa3-ac69-18b635a21374": "드루이드 유적",
    "83caafaa-5abc-40e4-8225-54136c4d2841": "희미한 페이지",
    "c10ff94a-0671-4618-9c27-2dda9c1fe87c": "희미한 페이지",
    "ee6938b6-6681-4d11-bbd9-98244ad4b961": "희미한 페이지",
    "fd312b2d-afcd-43c2-bfeb-0a2666328ed3": "희미한 페이지",
    "35a3ce58-66ef-4e9a-8d4c-22e32298c990": "무자비함의 손가락 반지",
    "6e57141b-281b-4160-a520-7289d4f30da1": "향기로운 꽃",
    "6ea46c54-be5d-4e2f-9bfa-0fa49587398b": "얼음의 심장",
    "19943865-9e02-46c8-93c2-1a3d4454c45d": "지옥불 브레이서",
    "5ab3b1e0-e4f9-42aa-b309-8db89a59a0e4": "아이스 코팅 페이지",
    "ce1654d9-2712-450d-872d-6b51566053dc": "아이스 코팅 페이지",
    "d96e588c-7e18-4faf-bdcf-3c4dc1fe03d4": "아이스 코팅 페이지",
    "76edd2e4-348d-4e08-8579-79dc2ca7365a": "칼날은 오해의 소지가 있을 정도로 약해 보입니다.",
    "1927f21d-62f3-4fe1-be89-cfced87b7d91": "켈리드 장비",
    "37d36eef-9ab1-47df-bb7b-2f3589d6ebb6": "맨티코어 꼬리",
    "fe050c13-24c8-46d0-bdc0-098d31fbd8d2": "약용 꽃",
    "87498494-7faa-4413-9955-847baf14f1c4": "자정 도리깨",
    "31b9e98c-b47c-42f4-8d53-bcd794bc7fee": "하루에 한 번, 이 천연 방어력 +3의 부적을 착용하면 10분 동안 착용자와 함께 싸우는 CR 7의 성스러운 사슴을 소환할 수 있습니다.",
    "0bd33b4e-c3f8-4a41-9e24-f96483c3b7ed": "화살통",
    "3047e203-6852-41ac-b312-6b235dba77b0": "드루카이트 화살의 화살통",
    "c0fb4a9d-4660-4019-abe9-013de941adc8": "희귀 꽃",
    "07ff8d10-f3b1-4f3b-beaf-2c8e1fa258b6": "원시 신성 힘의 반지",
    "8e2e10f4-0d24-4baa-9c29-8a70b2751146": "그림자 훔치는 반지",
    "c3395dd7-dc5b-4e30-b803-0ea28b32d41c": "주문 수행자의 가장자리",
    "63b8c0ff-3013-4606-8ae2-7f84177252ec": "에라스틸의 사슴 소환",
    "a42686cd-b860-477e-a59a-2ae23fdfa906": "드루카이트는 검은색과 보라색 광석으로, 너무 어두워서 생명체는 이를 인식하기 매우 어렵습니다. 드루카이트 광맥이 박힌 근접 무기를 사용하면 10%의 확률로 적에게 공격자가 투명인간인 것처럼 {g|Encyclopedia:Attack}공격({/g}이 다가오는 것을 보지 못할 수 있습니다.",
    "2d7142d2-a8ab-442e-a471-5a8d22b319cd": "족장 바르사그의 얼어붙은 심장이 이제 그의 벨트와 융합되었습니다. 이 벨트의 착용자는 {g|Encyclopedia:Armor_Class}AC{/g}에 +4 강화 {g|Encyclopedia:Bonus}보너스{/g}, {g|Encyclopedia:Energy_Immunity}냉기에 대한 면역{/g}, {g|Encyclopedia:Constitution}건강{/g}에 +4 보너스를 얻습니다.\n또한 하루에 한 번, 착용자는 얼음 폭포 능력을 {g|Encyclopedia:Standard_Actions}표준 행동{/g}으로 사용할 수 있습니다.\n얼음 폭포: 얼음과 눈 덩어리가 중간 범위 내의 적에게 부딪힌 후 튕겨나가 2차 목표물을 공격합니다. 이러한 대상은 주 대상에서 20피트 이내에 있어야 하며, 어떤 대상도 두 번 이상 공격할 수 없습니다. 각 대상은 {g|Encyclopedia:Dice}6d6{/g} {g|Encyclopedia:Energy_Damage}냉기 피해{/g}를 받고 단단한 얼음에 갇혀 {g|Encyclopedia:Combat_Round}1 라운드{/g} 동안 {g|ConditionParalyzed}마비{/g} 상태가 됩니다. {g|Encyclopedia:DC}DC{/g} 18 {g|Encyclopedia:Saving_Throw}반사 굴림{/g}에 성공하면 {g|Encyclopedia:Damage}피해{/g}가 절반으로 감소하고 마비가 무효화됩니다.",
    "8d452662-ac88-41db-ad57-8f3eba9132b2": "이 랜턴의 빛은 착용자와 20피트 내의 아군에게 그림자 베일 {g|Encyclopedia:Damage}피해{/g}를 방지합니다.\n불을 켜면 그림자 악마의 주의를 끌 수 있습니다.",
    "a9600b94-9e2a-4c28-bc28-1105174ce9c3": "미친 노인은 이 꽃을 가슴에 품고 살았습니다.",
    "750ed524-549a-4b01-8177-efd361fd7a62": "아스자트라고 알려진 남청색 광석은 주변의 모든 빛을 흡수합니다.{/g} 아스자이트 광맥 갑옷을 착용하면 {g|Encyclopedia:Stealth}은신 판정{/g}에서 +5의 상황 {g|Encyclopedia:Bonus}보너스{/g}를 받습니다. 착용자가 드루카이트 무기를 휘두르는 경우, 적에게 해당 무기로 {g|Encyclopedia:Attack}공격{/g}이 가해지는 것을 알아차리지 못할 확률이 20%로 증가합니다.",
    "698f1276-4a78-49e6-9b72-7ceda2a3dbb2": "이 화살통의 소유자는 이 화살통을 사용해 드루카이트 화살 50발을 발사할 수 있습니다. 드루카이트 광맥 화살은 공격자가 투명인간인 것처럼 적에게 50% 확률로 공격 사실을 알아차리지 못하게 합니다.",
    "86f7db95-5708-4187-a2e8-2e67423e408d": "페이지가 퀼의 날카로운 끝으로 찢어져 텍스트의 일부가 읽을 수 없게 된 것 같습니다.\n\"...ds!\nAl... co... sn...\n...o ...s.\nSp... in ...ts.\n나는 스승의 몰락에서 살아남았다. 얼어붙은 황무지를 헤매고 있다. 굶주림, 박해, 옛 동료들과의 싸움.\n이 모든 것이 미끄러져 이 저주받은 난간으로 떨어졌습니다!\n얼어붙은 군주의 진정한 종들이 이 메모를 발견하면, 제가 숨겨둔 보급품을 찾아주세요. 그 자리에는 시스후드의 상징이 표시되어 있습니다.\"",
    "bfd95140-ae60-455a-849d-132b504d03b4": "이 두꺼운 책의 노랗게 물든 페이지에는 메모가 가득합니다. 금박으로 장식된 술에는 다음 구절이 적혀 있습니다:\n\"...한때 주부미락의 얼음 심연의 황무지를 지배했던 시스후드의 이야기는 가장 흥미로운 이야기입니다. 악마 군주들은 종종 자신의 외모와 취향에 맞게 자신의 왕국을 선택하거나 재구성하는데, 언데드의 얼어붙은 군주 시스후드도 예외는 아니었습니다. 끝없이 펼쳐진 설원, 날카로운 얼음 능선, 산더미처럼 쌓인 죽은 자의 얼어붙은 뼈, 산 자의 뼈에서 살을 발라내는 사나운 바람... 그의 왕국이 어떤 모습일지 상상할 수 있을 거예요. 또 다른 악마 코스트치치가 자신의 영역을 부러워하며 바라보기 시작할 때까지 그는 세 손가락 발톱으로 쥬부미락을 단단히 붙잡았다.\n본래 자기중심적이고 경쟁심이 강한 악마들은 서로를 잡아먹음으로써 초자연적인 힘을 얻으며, 동료를 충분히 잡아먹은 악마는 초기 악마 군주가 될 수 있습니다. 이 생명체들은 심연의 어떤 군주에게도 도전할 수 있지만, 아직 자신의 칭호를 얻지는 못했습니다. 시스후드에게 도전하여 상당한 힘의 불균형에도 불구하고 그를 물리쳤던 코스트치도 그런 신생 존재 중 하나였습니다. 젊은 악마에게 유리하게 작용한 또 다른 요인이 있었을 것으로 추측할 수 있지만, 그 전투의 세부 사항은 여전히 베일에 싸여 있습니다. 코스트치치에게 어떤 비밀 무기가 있었을까요, 아니면 시스후드가 어떤 이유에서인지 약해져서 제대로 싸울 수 없었을까요? 미래 세대의 야심 찬 악마학자들이 이 수수께끼를 풀어주기를 기대해봅니다.\n그렇게 코스트치치는 시스후드의 성을 점령하고 오늘날까지 주부미락을 통치하고 있습니다. 시스후드 자신은 어땠을까요? 오랫동안 시스후드는 죽은 것으로 추정되어 왔으며, 그의 영혼은 패배한 악마 군주들이 육신을 잃은 후 가는 심연의 외딴 곳에 있는 안식의 균열에서 영원히 잠들어 있었습니다. 하지만 최근 발견한 바에 따르면 시스후드는 계급만 잃었을 뿐 목숨은 잃지 않은 것으로 밝혀졌습니다. 이는 완전한 악마 군주가 초기 악마 군주보다 낮은 계급으로 '강등'된 유일한 사례로 알려져 있습니다. 그는 의심할 여지없이 여전히 주부미락 산 어딘가에 죽음의 서리로부터 숨어 있으며, 천천히 힘을 되찾고 재대결을 위해 자원을 모으고 있습니다.\"",
    "a25d0fc8-193c-4848-b3f2-f5bb3fe7f81a": "이 팔찌를 착용하면 하루에 한 번 {g|SpellsHellfireRay}지옥불 광선{/g} {g|Encyclopedia:Spell}주문{/g}을 시전할 수 있습니다. 주문은 광선 3개를 발사하며, 각 광선은 {g|Encyclopedia:Dice}10d6{/g} {g|Encyclopedia:Damage}피해{/g}를 줍니다. 또한 착용자의 {g|Encyclopedia:Caster_Level}시전자 레벨{/g}이 1 증가합니다.",
    "74ac2289-7149-46bc-9536-429ce2239292": "이 +3의 사악한 드루카이트 도리깨는 현재 공격력 {g|Encyclopedia:HP}이 착용자의 공격력{/g} 보다 낮은 적에게 추가로 {g|Encyclopedia:Dice}1d6{/g} {g|Encyclopedia:Energy_Damage}부정한 피해{/g}를 입힙니다.",
    "6c7c7604-1528-497e-af1b-fc9c853b6046": "{/g}이 반지는 착용자에게 {g|Encyclopedia:Strength}힘{/g} {g|Encyclopedia:Ability_Scores}능력 점수{/g}에 +2 {g|Encyclopedia:Bonus}보너스{/g}를 부여합니다. 착용자는 언데드에 대한 {g|Encyclopedia:Attack}명중 굴림{/g}에 +2의 강화 보너스를 얻습니다. 하루에 한 번, 이 반지를 사용하여 {g|SpellsPrayer}기도{/g} {g|Encyclopedia:Spell}주문{/g}을 5회 {g|Encyclopedia:Combat_Round}라운드{/g} 동안 시전할 수 있습니다.",
    "049333bb-35fd-4c49-8772-4af16b4c617c": "이 반지는 착용자에게 최대 명중 지점에 도달하지 않은 대상에 대한 {g|Encyclopedia:Attack}공격{/g} 및 {g|Encyclopedia:Damage}피해{/g} 굴림에 +2의 성스러운 {g|Encyclopedia:Bonus}보너스{/g}를 부여합니다.",
    "5f47ee3c-ae57-4d0a-af65-b17a1bdb58b8": "이 날카로운 파편은 촉감이 부자연스럽게 차갑습니다.",
    "7786c150-7f9c-4a42-afff-2cc1e65095bf": "스토라스타의 고대 수호자의 오랜 세월에 낡은 지상 유물입니다.",
    "845ef8f3-cfe4-44e4-a658-5cc621c8e907": "이 마법의 식물을 섭취하면 {g|SpellsBarkskin}나무껍질{/g} {g|Encyclopedia:Spell}주문{/g} 과 유사한 효과를 얻을 수 있습니다.",
    "ae8bd3d9-9b8b-4f71-8424-f5c21c141df5": "이 +2 휴먼 베인 룬 마법검 결투검을 마법사가 휘두르면, 착용자에게 {g|Encyclopedia:Attack}명중 굴림{/g} 시 +2 통찰력 {g|Encyclopedia:Bonus}보너스{/g}를 부여합니다.",
    "85d10a93-dd81-49c9-9792-e6d09b6cb2a6": "{/g} 이 +2 아자이트 풀 플레이트 착용자가 {g|Encyclopedia:Critical}치명타({/g})를 받을 때마다, 1회의 {g|Encyclopedia:Combat_Round}라운드({/g})에 대해 {g|Encyclopedia:Concealment}은폐(20%의 적중 확률)를 얻습니다.",
    "2fb0391f-6cca-4522-815d-516c2642c92d": "이 반지를 착용한 자가 적을 처치할 때마다 10%의 확률로 반지가 적의 그림자를 훔쳐내어 5회 {g|Encyclopedia:Combat_Round}동안 착용자와 함께 싸우는 CR 9의 탐욕스러운 큰 그림자를 소환합니다{/g}. 반지가 그림자를 훔치고 나면 1분 동안 이 능력을 다시 발동할 수 없습니다.",
    "8a4b43b2-aca2-4895-b1fb-de98de05ed09": "이 +2 잔인한 팔치온을 휘두르는 자가 어떤 대상에게 이 무기로 {g|Encyclopedia:Critical}치명타{/g}를 가하면, 즉시 해당 대상에게 {g|Encyclopedia:Attack}공격{/g}을 한 번 더 가합니다{/g}이 추가 공격은 {g|Encyclopedia:Combat_Round}라운드{/g} 당 두 번 이상 발생할 수 없습니다.",
    "a4ad1ddf-3ef6-43cd-83b8-a721a74f51d1": "이 +2 출혈 드루카이트 단검이 적에게 적중할 때마다, 그 적은 1 {g|Encyclopedia:Combat_Round}라운드 동안{/g} 에 현혹됩니다.",
    "b08b07e8-8b8f-4fb2-b642-81a174a8ae38": "이 부츠의 착용자는 부상을 입은 동안 {g|Encyclopedia:Speed}이동 속도{/g}에 +30 {g|Encyclopedia:Bonus}보너스{/g}를 받고 이동 시 {g|Encyclopedia:Attack_Of_Opportunity}기회 공격{/g}을 유발하지 않습니다."
}